{
  "name": "",
  "auto": true,
  "responses": [
    {
      "text": {
        "text": [
          "it's the middle of summer, it shouldn't rain today.",
          "that would be weird.",
          "yes, it would be.",
          "in the middle of the summer, it shouldn't be raining.",
          "that wouldn't seem right."
        ]
      }
    }
  ],
  "priority": 500000,
  "webhookUsed": false,
  "webhookForSlotFilling": false,
  "fallbackIntent": false,
  "mlEnabled": true,
  "trainingPhrases": [
    {
      "type": "EXAMPLE",
      "parts": [
        {
          "text": "i know. i think it may rain."
        }
      ]
    },
    {
      "type": "EXAMPLE",
      "parts": [
        {
          "text": "it's the middle of summer, it shouldn't rain today."
        }
      ]
    },
    {
      "type": "EXAMPLE",
      "parts": [
        {
          "text": "i know, it would be horrible if it rained and it was hot outside."
        }
      ]
    },
    {
      "type": "EXAMPLE",
      "parts": [
        {
          "text": "you're right. i think it's going to rain later."
        }
      ]
    },
    {
      "type": "EXAMPLE",
      "parts": [
        {
          "text": "in the middle of the summer, it shouldn't be raining."
        }
      ]
    },
    {
      "type": "EXAMPLE",
      "parts": [
        {
          "text": "exactly, it wouldn't be nice if it started raining. it's too hot."
        }
      ]
    },
    {
      "type": "EXAMPLE",
      "parts": [
        {
          "text": "that is true. i hope it doesn't rain."
        }
      ]
    },
    {
      "type": "EXAMPLE",
      "parts": [
        {
          "text": "it wouldn't rain in the middle of the summer."
        }
      ]
    },
    {
      "type": "EXAMPLE",
      "parts": [
        {
          "text": "it wouldn't seem right if it started raining right now."
        }
      ]
    },
    {
      "type": "EXAMPLE",
      "parts": [
        {
          "text": "it would be weird if it started raining in ninety degree weather."
        }
      ]
    },
    {
      "type": "EXAMPLE",
      "parts": [
        {
          "text": "any rain right now would be pointless."
        }
      ]
    },
    {
      "type": "EXAMPLE",
      "parts": [
        {
          "text": "it looks like it may rain soon."
        }
      ]
    },
    {
      "type": "EXAMPLE",
      "parts": [
        {
          "text": "i really love how rain clears the air."
        }
      ]
    },
    {
      "type": "EXAMPLE",
      "parts": [
        {
          "text": "me too. it always smells so fresh after it rains."
        }
      ]
    },
    {
      "type": "EXAMPLE",
      "parts": [
        {
          "text": "yes, but i love the night air after it rains."
        }
      ]
    },
    {
      "type": "EXAMPLE",
      "parts": [
        {
          "text": "i really hope it rains today."
        }
      ]
    },
    {
      "type": "EXAMPLE",
      "parts": [
        {
          "text": "it seems that it may rain today."
        }
      ]
    },
    {
      "type": "EXAMPLE",
      "parts": [
        {
          "text": "i like how clear the sky gets after it rains."
        }
      ]
    },
    {
      "type": "EXAMPLE",
      "parts": [
        {
          "text": "i feel the same way. it smells so good after it rains."
        }
      ]
    },
    {
      "type": "EXAMPLE",
      "parts": [
        {
          "text": "i especially love the night air when it rains."
        }
      ]
    },
    {
      "type": "EXAMPLE",
      "parts": [
        {
          "text": "the stars look so much closer after it rains."
        }
      ]
    },
    {
      "type": "EXAMPLE",
      "parts": [
        {
          "text": "i really want it to rain today."
        }
      ]
    },
    {
      "type": "EXAMPLE",
      "parts": [
        {
          "text": "i think that it's going to rain."
        }
      ]
    },
    {
      "type": "EXAMPLE",
      "parts": [
        {
          "text": "i hope that it does rain."
        }
      ]
    },
    {
      "type": "EXAMPLE",
      "parts": [
        {
          "text": "you like the rain?"
        }
      ]
    },
    {
      "type": "EXAMPLE",
      "parts": [
        {
          "text": "the sky looks so clean after it rains. i love it."
        }
      ]
    },
    {
      "type": "EXAMPLE",
      "parts": [
        {
          "text": "i understand. rain does make it smell cleaner."
        }
      ]
    },
    {
      "type": "EXAMPLE",
      "parts": [
        {
          "text": "i love most how it is at night after it rains."
        }
      ]
    },
    {
      "type": "EXAMPLE",
      "parts": [
        {
          "text": "you can see the stars so much more clearly after it rains."
        }
      ]
    },
    {
      "type": "EXAMPLE",
      "parts": [
        {
          "text": "that sounds like fun. what's the weather going to be like?"
        }
      ]
    },
    {
      "type": "EXAMPLE",
      "parts": [
        {
          "text": "is it going to be perfect beach weather?"
        }
      ]
    },
    {
      "type": "EXAMPLE",
      "parts": [
        {
          "text": "but you know that california weather is really unpredictable."
        }
      ]
    },
    {
      "type": "EXAMPLE",
      "parts": [
        {
          "text": "i really wish the weather would just stay the same."
        }
      ]
    },
    {
      "type": "EXAMPLE",
      "parts": [
        {
          "text": "a trip to the beach would be fun. how is the weather going to be?"
        }
      ]
    },
    {
      "type": "EXAMPLE",
      "parts": [
        {
          "text": "so do you think it'll be perfect weather for the beach?"
        }
      ]
    },
    {
      "type": "EXAMPLE",
      "parts": [
        {
          "text": "the weather in california is unpredictable, so you never know."
        }
      ]
    },
    {
      "type": "EXAMPLE",
      "parts": [
        {
          "text": "that is true. the weather is constantly changing."
        }
      ]
    },
    {
      "type": "EXAMPLE",
      "parts": [
        {
          "text": "it would be nice if the weather would never change."
        }
      ]
    },
    {
      "type": "EXAMPLE",
      "parts": [
        {
          "text": "what's the weather going to be like? i may want to go too."
        }
      ]
    },
    {
      "type": "EXAMPLE",
      "parts": [
        {
          "text": "the weather this weekend is supposed to be warm."
        }
      ]
    },
    {
      "type": "EXAMPLE",
      "parts": [
        {
          "text": "will it be good beach weather?"
        }
      ]
    },
    {
      "type": "EXAMPLE",
      "parts": [
        {
          "text": "this california weather is so uncertain, it's impossible to know what'll happen."
        }
      ]
    },
    {
      "type": "EXAMPLE",
      "parts": [
        {
          "text": "i know. every day the weather seems different."
        }
      ]
    },
    {
      "type": "EXAMPLE",
      "parts": [
        {
          "text": "i'm still feeling under the weather."
        }
      ]
    },
    {
      "type": "EXAMPLE",
      "parts": [
        {
          "text": "it has great weather all year long."
        }
      ]
    },
    {
      "type": "EXAMPLE",
      "parts": [
        {
          "text": "they talk about food and the weather."
        }
      ]
    },
    {
      "type": "EXAMPLE",
      "parts": [
        {
          "text": "what's the weather like?"
        }
      ]
    },
    {
      "type": "EXAMPLE",
      "parts": [
        {
          "text": "okay. it looks like rain."
        }
      ]
    },
    {
      "type": "EXAMPLE",
      "parts": [
        {
          "text": "is it raining right now?"
        }
      ]
    },
    {
      "type": "EXAMPLE",
      "parts": [
        {
          "text": "what's the weather going to be like this weekend?"
        }
      ]
    },
    {
      "type": "EXAMPLE",
      "parts": [
        {
          "text": "i don't know. whenever the weather comes on, i switch channels."
        }
      ]
    },
    {
      "type": "EXAMPLE",
      "parts": [
        {
          "text": "it got rained out."
        }
      ]
    },
    {
      "type": "EXAMPLE",
      "parts": [
        {
          "text": "rained out?"
        }
      ]
    },
    {
      "type": "EXAMPLE",
      "parts": [
        {
          "text": "yes, rained out."
        }
      ]
    },
    {
      "type": "EXAMPLE",
      "parts": [
        {
          "text": "well, you can't play baseball in a rainstorm."
        }
      ]
    },
    {
      "type": "EXAMPLE",
      "parts": [
        {
          "text": "what's the weather like?"
        }
      ]
    },
    {
      "type": "EXAMPLE",
      "parts": [
        {
          "text": "the weatherman tells us the temperature in every town."
        }
      ]
    },
    {
      "type": "EXAMPLE",
      "parts": [
        {
          "text": "how was the weather?"
        }
      ]
    },
    {
      "type": "EXAMPLE",
      "parts": [
        {
          "text": "well, of course i want to go when the weather is nice."
        }
      ]
    }
  ]
}